{
  "需求编号": "1",
  "需求描述": "管理系统",
  "子功能1": "系统租户管理",
  "子功能2": "创建租户、注销租户",
  "子功能3": "在系统中创建和注销企业/个人租户",
  "对应功能项": "系统管理",
  "对应子功能1": "用户管理",
  "对应子功能2": "用户录入",
  "对应子功能3": "",
  "测试用例编号": "TC_1_1_1",
  "测试用例名称": "在用户录入界面，“用户账号”输入长度范围内的合法字符，其他参数填写正确，点击提交，录入用户成功",
  "预置条件": "1.服务端可以正常登陆",
  "操作步骤": "1.进入 系统管理-用户管理 页面\n2.点击 用户录入\n3.“用户账号”输入长度范围内的合法字符，其他参数填写正确，点击提交",
  "预期输出": "3.录入用户成功",
  "重要级别": 1,
  "测试类型": "功能测试",
  "适用阶段": "系统测试阶段",
  "测试结果": "通过",
  "最近执行人": "胡明明",
  "备注": "",
  "创建时间": "2025-07-10",
  "can_automate": true
}