{
  "需求编号": "27",
  "需求描述": "管理系统",
  "子功能1": "设备管理",
  "子功能2": "设备多级分组管理",
  "子功能3": "2.编辑设备分组",
  "对应功能项": "设备管理",
  "对应子功能1": "编辑分组",
  "对应子功能2": "",
  "对应子功能3": "",
  "测试用例编号": "TC_27_1_1",
  "测试用例名称": "在设备管理界面，存在分组A/B/C ，选择分组C，点击“编辑分组”，修改分组名称为D成功",
  "预置条件": "1.服务端可以正常登陆\n2.存在分组A/B/C",
  "操作步骤": "1.登陆服务端界面\n2.选择设备管理界面\n3.选择分组C，点击“编辑分组”，修改分组名称为D",
  "预期输出": "3.分组名称修改成功",
  "重要级别": 1,
  "测试类型": "功能测试",
  "适用阶段": "系统测试阶段",
  "测试结果": "通过",
  "最近执行人": "",
  "备注": "",
  "创建时间": "2025-07-10",
  "can_automate": true
}